<annotation>
	<folder>NASA</folder>
	<filename>5a16d85264621a493aebe5f1-large.jpg</filename>
	<path>/home/ajackow/Workspace/OpenCVML/traningData/NASA/5a16d85264621a493aebe5f1-large.jpg</path>
	<source>
		<database>Unknown</database>
	</source>
	<size>
		<width>600</width>
		<height>600</height>
		<depth>3</depth>
	</size>
	<segmented>0</segmented>
	<object>
		<name>NASA</name>
		<pose>Unspecified</pose>
		<truncated>0</truncated>
		<difficult>0</difficult>
		<bndbox>
			<xmin>123</xmin>
			<ymin>51</ymin>
			<xmax>143</xmax>
			<ymax>72</ymax>
		</bndbox>
	</object>
	<object>
		<name>NASA</name>
		<pose>Unspecified</pose>
		<truncated>0</truncated>
		<difficult>0</difficult>
		<bndbox>
			<xmin>123</xmin>
			<ymin>197</ymin>
			<xmax>143</xmax>
			<ymax>218</ymax>
		</bndbox>
	</object>
	<object>
		<name>NASA</name>
		<pose>Unspecified</pose>
		<truncated>0</truncated>
		<difficult>0</difficult>
		<bndbox>
			<xmin>247</xmin>
			<ymin>179</ymin>
			<xmax>398</xmax>
			<ymax>308</ymax>
		</bndbox>
	</object>
	<object>
		<name>NASA</name>
		<pose>Unspecified</pose>
		<truncated>0</truncated>
		<difficult>0</difficult>
		<bndbox>
			<xmin>119</xmin>
			<ymin>344</ymin>
			<xmax>143</xmax>
			<ymax>363</ymax>
		</bndbox>
	</object>
	<object>
		<name>NASA</name>
		<pose>Unspecified</pose>
		<truncated>0</truncated>
		<difficult>0</difficult>
		<bndbox>
			<xmin>119</xmin>
			<ymin>481</ymin>
			<xmax>146</xmax>
			<ymax>504</ymax>
		</bndbox>
	</object>
	<object>
		<name>NASA</name>
		<pose>Unspecified</pose>
		<truncated>0</truncated>
		<difficult>0</difficult>
		<bndbox>
			<xmin>501</xmin>
			<ymin>340</ymin>
			<xmax>561</xmax>
			<ymax>387</ymax>
		</bndbox>
	</object>
	<object>
		<name>NASA</name>
		<pose>Unspecified</pose>
		<truncated>0</truncated>
		<difficult>0</difficult>
		<bndbox>
			<xmin>506</xmin>
			<ymin>200</ymin>
			<xmax>563</xmax>
			<ymax>244</ymax>
		</bndbox>
	</object>
	<object>
		<name>NASA</name>
		<pose>Unspecified</pose>
		<truncated>0</truncated>
		<difficult>0</difficult>
		<bndbox>
			<xmin>498</xmin>
			<ymin>40</ymin>
			<xmax>556</xmax>
			<ymax>87</ymax>
		</bndbox>
	</object>
	<object>
		<name>NASA</name>
		<pose>Unspecified</pose>
		<truncated>0</truncated>
		<difficult>0</difficult>
		<bndbox>
			<xmin>507</xmin>
			<ymin>481</ymin>
			<xmax>568</xmax>
			<ymax>531</ymax>
		</bndbox>
	</object>
</annotation>
